ppsaw/__init__.py
PPSAW-0.0.1.dist-info/LICENSE
PPSAW-0.0.1.dist-info/METADATA
PPSAW-0.0.1.dist-info/WHEEL
PPSAW-0.0.1.dist-info/top_level.txt
PPSAW-0.0.1.dist-info/RECORD
