Metadata-Version: 2.1
Name: PPSAW
Version: 0.0.1
Summary: A Python PandaScore API Wrapper
Home-page: https://github.com/Phosphorescentt/PPSAW
Author: Joshua "Phosphorescent" Mankelow
License: UNKNOWN
Project-URL: Bug Tracker, https://github.com/Phosphorescentt/PPSAW/issues
Platform: UNKNOWN
Classifier: Programming Language :: Python :: 3
Classifier: License :: OSI Approved :: GNU General Public License v3 or later (GPLv3+)
Classifier: Operating System :: OS Independent
Requires-Python: >=3.6
License-File: LICENSE
